LICENSE
MANIFEST.in
README.md
pyproject.toml
setup.py
xjobs/__init__.py
xjobs.egg-info/PKG-INFO
xjobs.egg-info/SOURCES.txt
xjobs.egg-info/dependency_links.txt
xjobs.egg-info/requires.txt
xjobs.egg-info/top_level.txt