Metadata-Version: 2.1
Name: xjobs
Version: 0.0.0
Summary: Management of jobs on clusters
Home-page: https://github.com/xsuite/xjobs
License: UNKNOWN
Platform: UNKNOWN
License-File: LICENSE
